readpass/__init__.py
readpass-0.0.4.dist-info/LICENSE
readpass-0.0.4.dist-info/METADATA
readpass-0.0.4.dist-info/WHEEL
readpass-0.0.4.dist-info/top_level.txt
readpass-0.0.4.dist-info/RECORD
