Metadata-Version: 2.1
Name: readpass
Version: 0.0.4
Summary: function to modify user input
Home-page: https://repl.it/@ChezCoder/readpass
Author: ChezCoder
Author-email: mrpizzaguyytb@gmail.com
License: UNKNOWN
Platform: UNKNOWN
Classifier: Programming Language :: Python :: 3
Classifier: License :: OSI Approved :: MIT License
Classifier: Operating System :: OS Independent
Requires-Python: >=3.6
